vast_threatbus/__init__.py
vast_threatbus/message_mapping.py
vast_threatbus/metrics.py
vast_threatbus/test_message_mapping.py
vast_threatbus/test_metrics.py
vast_threatbus/vast_threatbus.py
vast_threatbus-2022.5.16.dist-info/METADATA
vast_threatbus-2022.5.16.dist-info/WHEEL
vast_threatbus-2022.5.16.dist-info/entry_points.txt
vast_threatbus-2022.5.16.dist-info/top_level.txt
vast_threatbus-2022.5.16.dist-info/RECORD
