Metadata-Version: 2.1
Name: vast-threatbus
Version: 2022.5.16
Summary: Connect the open source telemetry engine VAST with Threat Bus, the open source threat intelligence dissemination layer
Home-page: https://github.com/tenzir/threatbus
Author: Tenzir
Author-email: engineering@tenzir.com
License: BSD 3-clause
Keywords: open source,vast,threatbus,Threat Bus,threat intelligence,TI,TI dissemination
Platform: UNKNOWN
Classifier: Development Status :: 4 - Beta
Classifier: License :: OSI Approved :: BSD License
Classifier: Operating System :: MacOS :: MacOS X
Classifier: Operating System :: POSIX :: Linux
Classifier: Topic :: Scientific/Engineering :: Information Analysis
Classifier: Topic :: Scientific/Engineering :: Interface Engine/Protocol Translator
Classifier: Topic :: Security
Classifier: Topic :: Software Development :: Object Brokering
Classifier: Topic :: System :: Distributed Computing
Requires-Python: >=3.7
Requires-Dist: black (>=19.10b)
Requires-Dist: dynaconf (!=3.1.8,>=3.1.4)
Requires-Dist: python-dateutil
Requires-Dist: pyzmq (>=19)
Requires-Dist: pyvast (>=1.0.0)
Requires-Dist: stix2 (>=3.0)
Requires-Dist: threatbus (>=2022.5.16)
